{
  "columnsInfo":[
    {
      "dataIndex":"id","filterDropdown":"","filterDropdownVisible":false,"onFilterDropdownVisibleChange":false,"render":"","sorter":true,"title":"序号","width":"5%"
    }
  ,
    {
      "dataIndex":"title","filterDropdown":"prop","filterDropdownVisible":false,"onFilterDropdownVisibleChange":true,"render":"","sorter":false,"title":"列名","width":"25%"
    }
  ,
    {
      "dataIndex":"width","filterDropdown":"prop","filterDropdownVisible":false,"onFilterDropdownVisibleChange":true,"render":"","sorter":false,"title":"列宽","width":"15%"
    }
  ,
    {
      "dataIndex":"columnAlign","filterDropdown":"prop","filterDropdownVisible":false,"onFilterDropdownVisibleChange":true,"render":"a","sorter":false,"title":"对齐方式","width":"15%"
    }
  ,
    {
      "dataIndex":"checked","filterDropdown":"prop","filterDropdownVisible":false,"onFilterDropdownVisibleChange":true,"render":"a","sorter":false,"title":"隐藏列","width":"15%"
    }
  ],"columns":[
  {
    "filters":[
      {
        "text":"billno","value":"12"
      }
    ],"dataIndex":"billno","expanded":"","id":1,"rendered":"a","sorter":true,"title":"编码","width":"10%"
  }
,
  {
    "filters":[
      {
        "text":"measureunitsid","value":"14"
      }
    ],"dataIndex":"name","expanded":"","id":2,"rendered":"a","sorter":true,"title":"名称","width":"15%"
  }
,
  {
    "filters":[
      {
        "text":"billno","value":"12"
      }
    ],"dataIndex":"measureunitsid","expanded":"/f7/aa","id":3,"rendered":"","sorter":true,"title":"计量单位","width":"15%"
  }
,
  {
    "filters":[
      {
        "text":"measureunitsid","value":"14"
      }
    ],"dataIndex":"aProp","expanded":"","id":4,"rendered":"","sorter":true,"title":"辅助属性","width":"35%"
  }
,
  {
    "filters":[
      {
        "text":"billno","value":"12"
      }
    ],"dataIndex":"amount","expanded":"","id":5,"rendered":"","sorter":true,"title":"数量","width":"15%"
  }
,
  {
    "filters":[
      {
        "text":"measureunitsid","value":"14"
      }
    ],"dataIndex":"date","expanded":"","id":6,"rendered":"","sorter":true,"title":"交货时间","width":"10%"
  }
],"info":
{
  "page":1,"results":1,"seed":"0e504e79add1a004","version":"1.1"
}
,"results":[
  {
    "aProp":"辅助属性8","amount":"42","billno":"23","className":"not-completed-deliver-row___3pIuT","date":"1999-05-08","id":
  {
    "name":"SSN","value":"070-06-3234"
  }
  ,"name":"K/3WEB化测试8","measureunitsid":"厘米"
  }
,
  {
    "aProp":"辅助属性3","amount":"24","billno":"37","className":"default-row___eggz5","date":"2002-08-23","id":
  {
    "name":"SSN","value":"070-06-3234"
  }
  ,"name":"K/3WEB化测试8","measureunitsid":"米"
  }
,
  {
    "aProp":"辅助属性4","amount":"87","billno":"88","className":"not-completed-deliver-row___3pIuT","date":"1983-05-10","id":
  {
    "name":"SSN","value":"070-06-3234"
  }
  ,"name":"K/3WEB化测试6","measureunitsid":"千克"
  }
,
  {
    "aProp":"辅助属性5","amount":"57","billno":"41","className":"not-completed-deliver-row___3pIuT","date":"1978-07-13","id":
  {
    "name":"SSN","value":"070-06-3234"
  }
  ,"name":"K/3WEB化测试4","measureunitsid":"厘米"
  }
,
  {
    "aProp":"辅助属性4","amount":"24","billno":"49","className":"not-check-row___fsy_t","date":"2008-06-16","id":
  {
    "name":"SSN","value":"070-06-3234"
  }
  ,"name":"K/3WEB化测试4","measureunitsid":"米"
  }
,
  {
    "aProp":"辅助属性6","amount":"15","billno":"72","className":"default-row___eggz5","date":"2016-05-15","id":
  {
    "name":"SSN","value":"070-06-3234"
  }
  ,"name":"K/3WEB化测试2","measureunitsid":"千克"
  }
,
  {
    "aProp":"辅助属性4","amount":"85","billno":"36","className":"default-row___eggz5","date":"1984-02-21","id":
  {
    "name":"SSN","value":"070-06-3234"
  }
  ,"name":"K/3WEB化测试2","measureunitsid":"厘米"
  }
,
  {
    "aProp":"辅助属性2","amount":"46","billno":"36","className":"not-completed-deliver-row___3pIuT","date":"1994-06-09","id":
  {
    "name":"SSN","value":"070-06-3234"
  }
  ,"name":"K/3WEB化测试8","measureunitsid":"米"
  }
,
  {
    "aProp":"辅助属性3","amount":"45","billno":"74","className":"not-check-row___fsy_t","date":"1991-06-29","id":
  {
    "name":"SSN","value":"070-06-3234"
  }
  ,"name":"K/3WEB化测试3","measureunitsid":"千克"
  }
,
  {
    "aProp":"辅助属性1","amount":"42","billno":"51","className":"not-completed-deliver-row___3pIuT","date":"1980-05-17","id":
  {
    "name":"SSN","value":"070-06-3234"
  }
  ,"name":"K/3WEB化测试6","measureunitsid":"厘米"
  }
,
  {
    "aProp":"辅助属性1","amount":"16","billno":"28","className":"not-completed-deliver-row___3pIuT","date":"1988-04-01","id":
  {
    "name":"SSN","value":"070-06-3234"
  }
  ,"name":"K/3WEB化测试7","measureunitsid":"米"
  }
,
  {
    "aProp":"辅助属性5","amount":"44","billno":"49","className":"not-check-row___fsy_t","date":"2002-11-20","id":
  {
    "name":"SSN","value":"070-06-3234"
  }
  ,"name":"K/3WEB化测试4","measureunitsid":"千克"
  }
,
  {
    "aProp":"辅助属性7","amount":"67","billno":"51","className":"not-completed-deliver-row___3pIuT","date":"1998-05-27","id":
  {
    "name":"SSN","value":"070-06-3234"
  }
  ,"name":"K/3WEB化测试8","measureunitsid":"厘米"
  }
,
  {
    "aProp":"辅助属性7","amount":"55","billno":"91","className":"not-completed-deliver-row___3pIuT","date":"2016-07-14","id":
  {
    "name":"SSN","value":"070-06-3234"
  }
  ,"name":"K/3WEB化测试5","measureunitsid":"米"
  }
,
  {
    "aProp":"辅助属性1","amount":"58","billno":"27","className":"not-check-row___fsy_t","date":"2011-01-05","id":
  {
    "name":"SSN","value":"070-06-3234"
  }
  ,"name":"K/3WEB化测试6","measureunitsid":"千克"
  }
,
  {
    "aProp":"辅助属性7","amount":"61","billno":"88","className":"default-row___eggz5","date":"2017-12-09","id":
  {
    "name":"SSN","value":"070-06-3234"
  }
  ,"name":"K/3WEB化测试3","measureunitsid":"厘米"
  }
,
  {
    "aProp":"辅助属性8","amount":"48","billno":"25","className":"not-completed-deliver-row___3pIuT","date":"2004-05-09","id":
  {
    "name":"SSN","value":"070-06-3234"
  }
  ,"name":"K/3WEB化测试5","measureunitsid":"米"
  }
,
  {
    "aProp":"辅助属性1","amount":"69","billno":"22","className":"default-row___eggz5","date":"2013-07-17","id":
  {
    "name":"SSN","value":"070-06-3234"
  }
  ,"name":"K/3WEB化测试8","measureunitsid":"千克"
  }
,
  {
    "aProp":"辅助属性1","amount":"37","billno":"31","className":"not-check-row___fsy_t","date":"2018-03-16","id":
  {
    "name":"SSN","value":"070-06-3234"
  }
  ,"name":"K/3WEB化测试7","measureunitsid":"厘米"
  }
,
  {
    "aProp":"辅助属性1","amount":"93","billno":"02","className":"not-check-row___fsy_t","date":"1999-07-05","id":
  {
    "name":"SSN","value":"070-06-3234"
  }
  ,"name":"K/3WEB化测试6","measureunitsid":"米"
  }
,
  {
    "aProp":"辅助属性6","amount":"57","billno":"23","className":"not-completed-deliver-row___3pIuT","date":"2007-03-08","id":
  {
    "name":"SSN","value":"070-06-3234"
  }
  ,"name":"K/3WEB化测试5","measureunitsid":"千克"
  }
,
  {
    "aProp":"辅助属性2","amount":"56","billno":"58","className":"not-completed-deliver-row___3pIuT","date":"1977-09-07","id":
  {
    "name":"SSN","value":"070-06-3234"
  }
  ,"name":"K/3WEB化测试1","measureunitsid":"厘米"
  }
,
  {
    "aProp":"辅助属性4","amount":"47","billno":"61","className":"not-completed-deliver-row___3pIuT","date":"1982-07-19","id":
  {
    "name":"SSN","value":"070-06-3234"
  }
  ,"name":"K/3WEB化测试4","measureunitsid":"米"
  }
,
  {
    "aProp":"辅助属性8","amount":"44","billno":"65","className":"not-completed-deliver-row___3pIuT","date":"2000-07-24","id":
  {
    "name":"SSN","value":"070-06-3234"
  }
  ,"name":"K/3WEB化测试7","measureunitsid":"千克"
  }
,
  {
    "aProp":"辅助属性4","amount":"63","billno":"56","className":"not-check-row___fsy_t","date":"2007-09-18","id":
  {
    "name":"SSN","value":"070-06-3234"
  }
  ,"name":"K/3WEB化测试4","measureunitsid":"厘米"
  }
,
  {
    "aProp":"辅助属性8","amount":"46","billno":"06","className":"not-completed-deliver-row___3pIuT","date":"1973-05-06","id":
  {
    "name":"SSN","value":"070-06-3234"
  }
  ,"name":"K/3WEB化测试4","measureunitsid":"米"
  }
,
  {
    "aProp":"辅助属性1","amount":"65","billno":"18","className":"default-row___eggz5","date":"1973-05-19","id":
  {
    "name":"SSN","value":"070-06-3234"
  }
  ,"name":"K/3WEB化测试8","measureunitsid":"千克"
  }
,
  {
    "aProp":"辅助属性2","amount":"63","billno":"41","className":"not-completed-deliver-row___3pIuT","date":"1986-10-24","id":
  {
    "name":"SSN","value":"070-06-3234"
  }
  ,"name":"K/3WEB化测试6","measureunitsid":"厘米"
  }
,
  {
    "aProp":"辅助属性9","amount":"14","billno":"64","className":"default-row___eggz5","date":"1985-01-26","id":
  {
    "name":"SSN","value":"070-06-3234"
  }
  ,"name":"K/3WEB化测试8","measureunitsid":"米"
  }
,
  {
    "aProp":"辅助属性5","amount":"66","billno":"53","className":"not-completed-deliver-row___3pIuT","date":"2016-05-06","id":
  {
    "name":"SSN","value":"070-06-3234"
  }
  ,"name":"K/3WEB化测试8","measureunitsid":"千克"
  }
,
  {
    "aProp":"辅助属性3","amount":"66","billno":"55","className":"not-check-row___fsy_t","date":"1993-01-02","id":
  {
    "name":"SSN","value":"070-06-3234"
  }
  ,"name":"K/3WEB化测试6","measureunitsid":"厘米"
  }
,
  {
    "aProp":"辅助属性5","amount":"88","billno":"20","className":"default-row___eggz5","date":"2017-10-21","id":
  {
    "name":"SSN","value":"070-06-3234"
  }
  ,"name":"K/3WEB化测试2","measureunitsid":"米"
  }
,
  {
    "aProp":"辅助属性4","amount":"75","billno":"87","className":"not-completed-deliver-row___3pIuT","date":"2006-06-10","id":
  {
    "name":"SSN","value":"070-06-3234"
  }
  ,"name":"K/3WEB化测试4","measureunitsid":"千克"
  }
,
  {
    "aProp":"辅助属性3","amount":"89","billno":"35","className":"not-completed-deliver-row___3pIuT","date":"2003-10-14","id":
  {
    "name":"SSN","value":"070-06-3234"
  }
  ,"name":"K/3WEB化测试4","measureunitsid":"厘米"
  }
,
  {
    "aProp":"辅助属性3","amount":"47","billno":"56","className":"not-check-row___fsy_t","date":"1998-02-28","id":
  {
    "name":"SSN","value":"070-06-3234"
  }
  ,"name":"K/3WEB化测试4","measureunitsid":"米"
  }
,
  {
    "aProp":"辅助属性9","amount":"45","billno":"44","className":"default-row___eggz5","date":"1995-01-27","id":
  {
    "name":"SSN","value":"070-06-3234"
  }
  ,"name":"K/3WEB化测试6","measureunitsid":"千克"
  }
,
  {
    "aProp":"辅助属性5","amount":"18","billno":"10","className":"not-completed-deliver-row___3pIuT","date":"1986-02-17","id":
  {
    "name":"SSN","value":"070-06-3234"
  }
  ,"name":"K/3WEB化测试3","measureunitsid":"厘米"
  }
,
  {
    "aProp":"辅助属性6","amount":"83","billno":"35","className":"default-row___eggz5","date":"1980-06-12","id":
  {
    "name":"SSN","value":"070-06-3234"
  }
  ,"name":"K/3WEB化测试8","measureunitsid":"米"
  }
,
  {
    "aProp":"辅助属性7","amount":"77","billno":"15","className":"not-completed-deliver-row___3pIuT","date":"1975-01-26","id":
  {
    "name":"SSN","value":"070-06-3234"
  }
  ,"name":"K/3WEB化测试2","measureunitsid":"千克"
  }
,
  {
    "aProp":"辅助属性8","amount":"44","billno":"90","className":"default-row___eggz5","date":"1972-11-01","id":
  {
    "name":"SSN","value":"070-06-3234"
  }
  ,"name":"K/3WEB化测试5","measureunitsid":"厘米"
  }
,
  {
    "aProp":"辅助属性9","amount":"86","billno":"61","className":"not-check-row___fsy_t","date":"1985-08-03","id":
  {
    "name":"SSN","value":"070-06-3234"
  }
  ,"name":"K/3WEB化测试3","measureunitsid":"米"
  }
,
  {
    "aProp":"辅助属性1","amount":"37","billno":"86","className":"not-completed-deliver-row___3pIuT","date":"1982-10-02","id":
  {
    "name":"SSN","value":"070-06-3234"
  }
  ,"name":"K/3WEB化测试4","measureunitsid":"千克"
  }
,
  {
    "aProp":"辅助属性2","amount":"33","billno":"32","className":"not-completed-deliver-row___3pIuT","date":"2018-04-27","id":
  {
    "name":"SSN","value":"070-06-3234"
  }
  ,"name":"K/3WEB化测试4","measureunitsid":"厘米"
  }
,
  {
    "aProp":"辅助属性8","amount":"55","billno":"98","className":"not-completed-deliver-row___3pIuT","date":"2017-01-11","id":
  {
    "name":"SSN","value":"070-06-3234"
  }
  ,"name":"K/3WEB化测试6","measureunitsid":"米"
  }
,
  {
    "aProp":"辅助属性4","amount":"84","billno":"48","className":"not-completed-deliver-row___3pIuT","date":"1991-09-08","id":
  {
    "name":"SSN","value":"070-06-3234"
  }
  ,"name":"K/3WEB化测试4","measureunitsid":"千克"
  }
,
  {
    "aProp":"辅助属性7","amount":"58","billno":"62","className":"not-completed-deliver-row___3pIuT","date":"1981-07-10","id":
  {
    "name":"SSN","value":"070-06-3234"
  }
  ,"name":"K/3WEB化测试5","measureunitsid":"厘米"
  }
,
  {
    "aProp":"辅助属性4","amount":"31","billno":"45","className":"default-row___eggz5","date":"1991-08-29","id":
  {
    "name":"SSN","value":"070-06-3234"
  }
  ,"name":"K/3WEB化测试8","measureunitsid":"米"
  }
,
  {
    "aProp":"辅助属性8","amount":"16","billno":"86","className":"default-row___eggz5","date":"2012-11-11","id":
  {
    "name":"SSN","value":"070-06-3234"
  }
  ,"name":"K/3WEB化测试3","measureunitsid":"千克"
  }
,
  {
    "aProp":"辅助属性4","amount":"44","billno":"12","className":"not-check-row___fsy_t","date":"1994-03-22","id":
  {
    "name":"SSN","value":"070-06-3234"
  }
  ,"name":"K/3WEB化测试2","measureunitsid":"厘米"
  }
,
  {
    "aProp":"辅助属性6","amount":"83","billno":"36","className":"not-check-row___fsy_t","date":"1984-02-04","id":
  {
    "name":"SSN","value":"070-06-3234"
  }
  ,"name":"K/3WEB化测试9","measureunitsid":"米"
  }
,
  {
    "aProp":"辅助属性5","amount":"64","billno":"32","className":"not-completed-deliver-row___3pIuT","date":"2018-04-28","id":
  {
    "name":"SSN","value":"070-06-3234"
  }
  ,"name":"K/3WEB化测试7","measureunitsid":"千克"
  }
,
  {
    "aProp":"辅助属性5","amount":"78","billno":"81","className":"not-completed-deliver-row___3pIuT","date":"1971-09-25","id":
  {
    "name":"SSN","value":"070-06-3234"
  }
  ,"name":"K/3WEB化测试4","measureunitsid":"厘米"
  }
,
  {
    "aProp":"辅助属性4","amount":"32","billno":"26","className":"not-completed-deliver-row___3pIuT","date":"1984-11-25","id":
  {
    "name":"SSN","value":"070-06-3234"
  }
  ,"name":"K/3WEB化测试5","measureunitsid":"米"
  }
,
  {
    "aProp":"辅助属性3","amount":"43","billno":"76","className":"not-completed-deliver-row___3pIuT","date":"1973-11-03","id":
  {
    "name":"SSN","value":"070-06-3234"
  }
  ,"name":"K/3WEB化测试4","measureunitsid":"千克"
  }
,
  {
    "aProp":"辅助属性7","amount":"55","billno":"08","className":"default-row___eggz5","date":"1993-08-27","id":
  {
    "name":"SSN","value":"070-06-3234"
  }
  ,"name":"K/3WEB化测试5","measureunitsid":"厘米"
  }
,
  {
    "aProp":"辅助属性4","amount":"96","billno":"22","className":"default-row___eggz5","date":"2010-08-12","id":
  {
    "name":"SSN","value":"070-06-3234"
  }
  ,"name":"K/3WEB化测试4","measureunitsid":"米"
  }
,
  {
    "aProp":"辅助属性5","amount":"38","billno":"20","className":"not-completed-deliver-row___3pIuT","date":"1994-12-06","id":
  {
    "name":"SSN","value":"070-06-3234"
  }
  ,"name":"K/3WEB化测试4","measureunitsid":"千克"
  }
,
  {
    "aProp":"辅助属性4","amount":"28","billno":"54","className":"not-completed-deliver-row___3pIuT","date":"1974-06-14","id":
  {
    "name":"SSN","value":"070-06-3234"
  }
  ,"name":"K/3WEB化测试6","measureunitsid":"厘米"
  }
,
  {
    "aProp":"辅助属性8","amount":"45","billno":"77","className":"not-completed-deliver-row___3pIuT","date":"1975-06-14","id":
  {
    "name":"SSN","value":"070-06-3234"
  }
  ,"name":"K/3WEB化测试8","measureunitsid":"米"
  }
,
  {
    "aProp":"辅助属性7","amount":"41","billno":"53","className":"not-check-row___fsy_t","date":"2004-05-08","id":
  {
    "name":"SSN","value":"070-06-3234"
  }
  ,"name":"K/3WEB化测试6","measureunitsid":"千克"
  }
,
  {
    "aProp":"辅助属性9","amount":"54","billno":"04","className":"not-completed-deliver-row___3pIuT","date":"1976-12-31","id":
  {
    "name":"SSN","value":"070-06-3234"
  }
  ,"name":"K/3WEB化测试3","measureunitsid":"厘米"
  }
,
  {
    "aProp":"辅助属性3","amount":"42","billno":"28","className":"not-completed-deliver-row___3pIuT","date":"2014-01-13","id":
  {
    "name":"SSN","value":"070-06-3234"
  }
  ,"name":"K/3WEB化测试6","measureunitsid":"米"
  }
,
  {
    "aProp":"辅助属性4","amount":"48","billno":"54","className":"not-completed-deliver-row___3pIuT","date":"2003-02-27","id":
  {
    "name":"SSN","value":"070-06-3234"
  }
  ,"name":"K/3WEB化测试3","measureunitsid":"千克"
  }
,
  {
    "aProp":"辅助属性7","amount":"78","billno":"67","className":"default-row___eggz5","date":"1997-07-28","id":
  {
    "name":"SSN","value":"070-06-3234"
  }
  ,"name":"K/3WEB化测试6","measureunitsid":"厘米"
  }
,
  {
    "aProp":"辅助属性1","amount":"25","billno":"25","className":"not-check-row___fsy_t","date":"2012-02-04","id":
  {
    "name":"SSN","value":"070-06-3234"
  }
  ,"name":"K/3WEB化测试8","measureunitsid":"米"
  }
,
  {
    "aProp":"辅助属性8","amount":"38","billno":"45","className":"not-completed-deliver-row___3pIuT","date":"2014-04-11","id":
  {
    "name":"SSN","value":"070-06-3234"
  }
  ,"name":"K/3WEB化测试4","measureunitsid":"千克"
  }
,
  {
    "aProp":"辅助属性5","amount":"88","billno":"36","className":"not-completed-deliver-row___3pIuT","date":"1988-03-06","id":
  {
    "name":"SSN","value":"070-06-3234"
  }
  ,"name":"K/3WEB化测试1","measureunitsid":"厘米"
  }
,
  {
    "aProp":"辅助属性7","amount":"55","billno":"86","className":"not-completed-deliver-row___3pIuT","date":"2003-02-13","id":
  {
    "name":"SSN","value":"070-06-3234"
  }
  ,"name":"K/3WEB化测试4","measureunitsid":"米"
  }
,
  {
    "aProp":"辅助属性3","amount":"74","billno":"43","className":"not-completed-deliver-row___3pIuT","date":"1971-11-17","id":
  {
    "name":"SSN","value":"070-06-3234"
  }
  ,"name":"K/3WEB化测试3","measureunitsid":"千克"
  }
,
  {
    "aProp":"辅助属性4","amount":"58","billno":"21","className":"not-completed-deliver-row___3pIuT","date":"1976-02-09","id":
  {
    "name":"SSN","value":"070-06-3234"
  }
  ,"name":"K/3WEB化测试9","measureunitsid":"厘米"
  }
,
  {
    "aProp":"辅助属性5","amount":"26","billno":"88","className":"not-check-row___fsy_t","date":"2003-11-12","id":
  {
    "name":"SSN","value":"070-06-3234"
  }
  ,"name":"K/3WEB化测试2","measureunitsid":"米"
  }
,
  {
    "aProp":"辅助属性8","amount":"42","billno":"41","className":"default-row___eggz5","date":"1989-01-26","id":
  {
    "name":"SSN","value":"070-06-3234"
  }
  ,"name":"K/3WEB化测试1","measureunitsid":"千克"
  }
,
  {
    "aProp":"辅助属性8","amount":"49","billno":"48","className":"default-row___eggz5","date":"1975-06-21","id":
  {
    "name":"SSN","value":"070-06-3234"
  }
  ,"name":"K/3WEB化测试4","measureunitsid":"厘米"
  }
,
  {
    "aProp":"辅助属性5","amount":"26","billno":"95","className":"not-check-row___fsy_t","date":"2011-10-23","id":
  {
    "name":"SSN","value":"070-06-3234"
  }
  ,"name":"K/3WEB化测试6","measureunitsid":"米"
  }
,
  {
    "aProp":"辅助属性7","amount":"41","billno":"85","className":"not-completed-deliver-row___3pIuT","date":"1971-06-26","id":
  {
    "name":"SSN","value":"070-06-3234"
  }
  ,"name":"K/3WEB化测试2","measureunitsid":"千克"
  }
,
  {
    "aProp":"辅助属性8","amount":"29","billno":"00","className":"not-check-row___fsy_t","date":"1974-07-17","id":
  {
    "name":"SSN","value":"070-06-3234"
  }
  ,"name":"K/3WEB化测试7","measureunitsid":"厘米"
  }
,
  {
    "aProp":"辅助属性6","amount":"68","billno":"39","className":"default-row___eggz5","date":"1994-04-18","id":
  {
    "name":"SSN","value":"070-06-3234"
  }
  ,"name":"K/3WEB化测试8","measureunitsid":"米"
  }
,
  {
    "aProp":"辅助属性4","amount":"49","billno":"73","className":"not-completed-deliver-row___3pIuT","date":"1999-09-07","id":
  {
    "name":"SSN","value":"070-06-3234"
  }
  ,"name":"K/3WEB化测试9","measureunitsid":"千克"
  }
,
  {
    "aProp":"辅助属性4","amount":"49","billno":"89","className":"not-completed-deliver-row___3pIuT","date":"2014-09-02","id":
  {
    "name":"SSN","value":"070-06-3234"
  }
  ,"name":"K/3WEB化测试2","measureunitsid":"厘米"
  }
,
  {
    "aProp":"辅助属性7","amount":"33","billno":"47","className":"not-completed-deliver-row___3pIuT","date":"1982-02-26","id":
  {
    "name":"SSN","value":"070-06-3234"
  }
  ,"name":"K/3WEB化测试1","measureunitsid":"米"
  }
,
  {
    "aProp":"辅助属性7","amount":"67","billno":"13","className":"not-completed-deliver-row___3pIuT","date":"1985-05-05","id":
  {
    "name":"SSN","value":"070-06-3234"
  }
  ,"name":"K/3WEB化测试5","measureunitsid":"千克"
  }
,
  {
    "aProp":"辅助属性8","amount":"28","billno":"06","className":"not-completed-deliver-row___3pIuT","date":"1998-09-11","id":
  {
    "name":"SSN","value":"070-06-3234"
  }
  ,"name":"K/3WEB化测试1","measureunitsid":"厘米"
  }
,
  {
    "aProp":"辅助属性9","amount":"94","billno":"80","className":"not-completed-deliver-row___3pIuT","date":"1973-01-25","id":
  {
    "name":"SSN","value":"070-06-3234"
  }
  ,"name":"K/3WEB化测试4","measureunitsid":"米"
  }
,
  {
    "aProp":"辅助属性3","amount":"56","billno":"58","className":"not-completed-deliver-row___3pIuT","date":"1989-07-29","id":
  {
    "name":"SSN","value":"070-06-3234"
  }
  ,"name":"K/3WEB化测试7","measureunitsid":"千克"
  }
,
  {
    "aProp":"辅助属性7","amount":"42","billno":"64","className":"not-completed-deliver-row___3pIuT","date":"1991-01-07","id":
  {
    "name":"SSN","value":"070-06-3234"
  }
  ,"name":"K/3WEB化测试4","measureunitsid":"厘米"
  }
,
  {
    "aProp":"辅助属性4","amount":"53","billno":"64","className":"default-row___eggz5","date":"1999-11-17","id":
  {
    "name":"SSN","value":"070-06-3234"
  }
  ,"name":"K/3WEB化测试6","measureunitsid":"米"
  }
,
  {
    "aProp":"辅助属性4","amount":"68","billno":"30","className":"not-check-row___fsy_t","date":"1993-05-17","id":
  {
    "name":"SSN","value":"070-06-3234"
  }
  ,"name":"K/3WEB化测试3","measureunitsid":"千克"
  }
,
  {
    "aProp":"辅助属性7","amount":"41","billno":"88","className":"not-completed-deliver-row___3pIuT","date":"1998-09-19","id":
  {
    "name":"SSN","value":"070-06-3234"
  }
  ,"name":"K/3WEB化测试5","measureunitsid":"厘米"
  }
,
  {
    "aProp":"辅助属性2","amount":"64","billno":"03","className":"not-completed-deliver-row___3pIuT","date":"1998-09-09","id":
  {
    "name":"SSN","value":"070-06-3234"
  }
  ,"name":"K/3WEB化测试3","measureunitsid":"米"
  }
,
  {
    "aProp":"辅助属性3","amount":"94","billno":"12","className":"not-check-row___fsy_t","date":"2013-02-25","id":
  {
    "name":"SSN","value":"070-06-3234"
  }
  ,"name":"K/3WEB化测试5","measureunitsid":"千克"
  }
,
  {
    "aProp":"辅助属性9","amount":"72","billno":"62","className":"not-completed-deliver-row___3pIuT","date":"1981-04-27","id":
  {
    "name":"SSN","value":"070-06-3234"
  }
  ,"name":"K/3WEB化测试3","measureunitsid":"厘米"
  }
,
  {
    "aProp":"辅助属性5","amount":"83","billno":"01","className":"default-row___eggz5","date":"1973-05-05","id":
  {
    "name":"SSN","value":"070-06-3234"
  }
  ,"name":"K/3WEB化测试4","measureunitsid":"米"
  }
,
  {
    "aProp":"辅助属性9","amount":"68","billno":"73","className":"default-row___eggz5","date":"2003-10-16","id":
  {
    "name":"SSN","value":"070-06-3234"
  }
  ,"name":"K/3WEB化测试9","measureunitsid":"千克"
  }
,
  {
    "aProp":"辅助属性2","amount":"84","billno":"61","className":"not-check-row___fsy_t","date":"2009-11-17","id":
  {
    "name":"SSN","value":"070-06-3234"
  }
  ,"name":"K/3WEB化测试4","measureunitsid":"厘米"
  }
,
  {
    "aProp":"辅助属性5","amount":"64","billno":"81","className":"default-row___eggz5","date":"1996-09-08","id":
  {
    "name":"SSN","value":"070-06-3234"
  }
  ,"name":"K/3WEB化测试9","measureunitsid":"米"
  }
,
  {
    "aProp":"辅助属性3","amount":"83","billno":"82","className":"not-completed-deliver-row___3pIuT","date":"1982-03-07","id":
  {
    "name":"SSN","value":"070-06-3234"
  }
  ,"name":"K/3WEB化测试8","measureunitsid":"千克"
  }
,
  {
    "aProp":"辅助属性8","amount":"47","billno":"06","className":"default-row___eggz5","date":"1989-01-23","id":
  {
    "name":"SSN","value":"070-06-3234"
  }
  ,"name":"K/3WEB化测试2","measureunitsid":"厘米"
  }
,
  {
    "aProp":"辅助属性2","amount":"34","billno":"35","className":"not-completed-deliver-row___3pIuT","date":"1991-06-15","id":
  {
    "name":"SSN","value":"070-06-3234"
  }
  ,"name":"K/3WEB化测试2","measureunitsid":"米"
  }
,
  {
    "aProp":"辅助属性9","amount":"95","billno":"35","className":"not-check-row___fsy_t","date":"2006-05-13","id":
  {
    "name":"SSN","value":"070-06-3234"
  }
  ,"name":"K/3WEB化测试4","measureunitsid":"千克"
  }
,
  {
    "aProp":"辅助属性5","amount":"76","billno":"29","className":"not-check-row___fsy_t","date":"1991-12-18","id":
  {
    "name":"SSN","value":"070-06-3234"
  }
  ,"name":"K/3WEB化测试8","measureunitsid":"厘米"
  }
]
}
